{
    "id": "https://osmt.wgu.edu/api/skills/60cb3d90-08e5-433f-b3a4-16740cd55d27",
    "uuid": "60cb3d90-08e5-433f-b3a4-16740cd55d27",
    "status": "published",
    "publishDate": "2022-02-04T15:25:39.275817",
    "archiveDate": null,
    "skillName": "Research Requests Resolution",
    "skillStatement": "Work closely with an accounting department to resolve any research requests and communicate any learned and potential results.",
    "category": "Research",
    "keywords": [
        "Research",
        "Basic Research",
        "Action Research",
        "Applied Research",
        "Clinical Research",
        "Educational Research",
        "Research And Development",
        "Research Design",
        "Research Experiences",
        "Research Methodologies",
        "Research Reports",
        "Research",
        "WGUSID: 6907"
    ],
    "occupations": [
        {
            "code": "13-0000",
            "targetNodeName": "Business and Financial Operations Occupations",
            "frameworkName": "bls"
        },
        {
            "code": "13-2010",
            "targetNodeName": "Accountants and Auditors",
            "frameworkName": "bls"
        },
        {
            "code": "13-2011",
            "targetNodeName": "Accountants and Auditors",
            "frameworkName": "bls"
        },
        {
            "code": "13-2030",
            "targetNodeName": "Budget Analysts",
            "frameworkName": "bls"
        },
        {
            "code": "13-2031",
            "targetNodeName": "Budget Analysts",
            "frameworkName": "bls"
        },
        {
            "code": "13-2040",
            "targetNodeName": "Credit Analysts",
            "frameworkName": "bls"
        },
        {
            "code": "13-2041",
            "targetNodeName": "Credit Analysts",
            "frameworkName": "bls"
        },
        {
            "code": "13-2060",
            "targetNodeName": "Financial Examiners",
            "frameworkName": "bls"
        },
        {
            "code": "13-2061",
            "targetNodeName": "Financial Examiners",
            "frameworkName": "bls"
        },
        {
            "code": "13-2080",
            "targetNodeName": "Tax Examiners, Collectors and Preparers, and Revenue Agents",
            "frameworkName": "bls"
        },
        {
            "code": "13-2081",
            "targetNodeName": "Tax Examiners and Collectors, and Revenue Agents",
            "frameworkName": "bls"
        }
    ],
    "slug": "research-requests-resolution"
}